airflow_training_operators-0.0.3.dist-info/METADATA
airflow_training_operators-0.0.3.dist-info/RECORD
airflow_training_operators-0.0.3.dist-info/WHEEL
airflow_training_operators-0.0.3.dist-info/top_level.txt
godatadriven/__init__.py
godatadriven/hooks/__init__.py
godatadriven/hooks/bigquery_hook.py
godatadriven/hooks/gcp_api_base_hook.py
godatadriven/operators/__init__.py
godatadriven/operators/gcs_to_bq.py
godatadriven/operators/postgres_to_gcs.py
