Metadata-Version: 2.1
Name: airflow-training-operators
Version: 0.0.3
Summary: Apache Airflow components that we use for the Airflow Training material
Home-page: https://github.com/godatadriven/airflow-training-operators
Author: Bas & Fokko
Author-email: signal@godatadriven.com
License: UNKNOWN
Platform: UNKNOWN
